.flake8
.gitignore
.travis.yml
CHANGELOG.rst
CONTRIBUTING.rst
LICENSE.txt
README.rst
environment.yml
nbval_sanitize.cfg
pytest.ini
setup.py
test_requirements.txt
binder/postBuild
docs/.gitignore
docs/.nojekyll
docs/CoV_Spike.nblink
docs/Makefile
docs/README.rst
docs/acknowledgments.rst
docs/cli.rst
docs/conf.py
docs/doc_requirements.txt
docs/examples.rst
docs/flu_HAs.nblink
docs/index.rst
docs/installation.rst
docs/nglview_example.nblink
docs/package_index.rst
docs/pymol_example.nblink
docs/_static/BloomLogo.jpg
notebooks/CoV_Spike.ipynb
notebooks/README.rst
notebooks/flu_HAs.ipynb
notebooks/nglview_example.ipynb
notebooks/pymol_example.ipynb
notebooks/input_files/4o5n_trimer.pdb
notebooks/input_files/6crv.pdb
notebooks/input_files/HA_H3_H4_H14.fa
notebooks/input_files/beta_coronavirus_Spikes.fa
notebooks/output_files/HA_H3_H4_H14_alignment.fa
notebooks/output_files/HA_H3_H4_H14_sites.csv
notebooks/output_files/HA_H3_H4_H14_unstripped_alignment.fa
notebooks/output_files/beta_coronavirus_Spike_alignment.fa
notebooks/output_files/beta_coronavirus_Spike_drop_refprot_alignment.fa
notebooks/output_files/beta_coronavirus_Spike_drop_refprot_sites.csv
notebooks/output_files/beta_coronavirus_Spike_drop_refprot_unstripped_alignment.fa
notebooks/output_files/beta_coronavirus_Spike_sites.csv
notebooks/output_files/beta_coronavirus_Spike_unstripped_alignment.fa
pdb_prot_align/__init__.py
pdb_prot_align/colorschemes.py
pdb_prot_align/genbank.py
pdb_prot_align/main.py
pdb_prot_align/nglview_struct.py
pdb_prot_align/pymol_struct.py
pdb_prot_align/utils.py
pdb_prot_align.egg-info/PKG-INFO
pdb_prot_align.egg-info/SOURCES.txt
pdb_prot_align.egg-info/dependency_links.txt
pdb_prot_align.egg-info/entry_points.txt
pdb_prot_align.egg-info/requires.txt
pdb_prot_align.egg-info/top_level.txt
tests/README.rst