Metadata-Version: 1.1
Name: pdb-prot-align
Version: 0.5.0
Summary: Align proteins to PDB chains
Home-page: https://github.com/jbloomlab/pdb_prot_align
Author: `the Bloom lab <https://research.fhcrc.org/bloom/en.html>`_
Author-email: jbloom@fredhutch.org
License: GPLv3
Download-URL: https://github.com/jbloomlab/pdb_prot_align/tarball/0.5.0
Platform: Linux and Mac OS X.
